sk_common/__init__.py
sk_common/db/__init__.py
sk_common/db/db_helper.py
sk_common/db/sqlserver_in_out.py
sk_common/file/__init__.py
sk_common/file/file_reader.py
sk_common/file/file_writer.py
sk_common-0.1.8.dist-info/LICENSE
sk_common-0.1.8.dist-info/METADATA
sk_common-0.1.8.dist-info/WHEEL
sk_common-0.1.8.dist-info/top_level.txt
sk_common-0.1.8.dist-info/RECORD
